[
    { "nombre": "Carlos Ampuero Carrión", "alfabetico": "Ampuero Carrión", "linkedin": "https://www.linkedin.com/in/carlos-ampuero-74b461b6/", "web": "https://www.carlosampuero.com/", "academico": "" },
    { "nombre": "Sebastián Aravena Ortiz", "alfabetico": "Aravena Ortiz", "linkedin": "https://www.linkedin.com/in/sebaaravena/", "web": "http://www.sebaaravena.cl/", "academico": "https://orcid.org/0000-0002-4974-9069" },
    { "nombre": "Patricio Araya Beltran*", "alfabetico": "Araya Beltran", "linkedin": "https://www.linkedin.com/in/patricio-araya-beltr%C3%A1n-43ba5651/", "web": "", "academico": "" },
    { "nombre": "Patricio Arias Cortés", "alfabetico": "Arias Cortés", "linkedin": "https://www.linkedin.com/in/patricio-arias-cortes-a1948935/", "web": "", "academico": "" },
    { "nombre": "María Isabel Barros McIntosh", "alfabetico": "Barros McIntosh", "linkedin": "https://www.linkedin.com/in/mar%C3%ADa-cristina-barros-mc-intosh-55b92442/", "web": "", "academico": "" },
    { "nombre": "Patricio Bascuñán Correa*", "alfabetico": "Bascuñán Correa", "linkedin": "", "web": "", "academico": "" },
    { "nombre": "Macarena Becas Villegas*", "alfabetico": "Becas Villegas", "linkedin": "https://www.linkedin.com/in/macarena-becas-b801861b/", "web": "", "academico": "" },
    { "nombre": "Jacob Bustamante Salazar*", "alfabetico": "Bustamante Salazar", "linkedin": "https://www.linkedin.com/in/jacobustamante/", "web": "", "academico": "" },
    { "nombre": "Andrea Cabello Cordero", "alfabetico": "Cabello Cordero", "linkedin": "https://www.linkedin.com/in/andreacabello/", "web": "", "academico": "" },
    { "nombre": "Marcos Calderón Cabrera", "alfabetico": "Calderón Cabrera", "linkedin": "https://www.linkedin.com/in/marcosfelipecalderon/?originalSubdomain=cl", "web": "", "academico": "" },
    { "nombre": "Juan Calderón Reyes", "alfabetico": "Calderón Reyes", "linkedin": "https://www.linkedin.com/in/juan-calder%C3%B3n-74431b47/", "web": "", "academico": "" },
    { "nombre": "Carla Cortés Hernández", "alfabetico": "Cortés Hernández", "linkedin": "https://www.linkedin.com/in/carla-cortes/", "web": "", "academico": "" },
    { "nombre": "Sol Díaz Castillo", "alfabetico": "Díaz Castillo", "linkedin": "", "web": "https://www.soldiaz.com/", "academico": "" },
    { "nombre": "Carlota Durán Vivanco", "alfabetico": "Durán Vivanco", "linkedin": "https://www.linkedin.com/in/carlota-duran-vivanco-3b076b20/", "web": "https://www.tejaverde.cl/", "academico": "" },
    { "nombre": "Daniel Ferrera Leiva*", "alfabetico": "Ferrera Leiva", "linkedin": "https://www.linkedin.com/in/daniel-ferrera-leiva-55a65590/", "web": "", "academico": "" },
    { "nombre": "Claudio Fredes Osses", "alfabetico": "Fredes Osses", "linkedin": "https://www.linkedin.com/in/claudiofredesosses/", "web": "https://www.claudiofredes.com/", "academico": "" },
    { "nombre": "Pamela Fuentes Villavicencio", "alfabetico": "Fuentes Villavicencio", "linkedin": "https://www.linkedin.com/in/pamela-fuentes-villavicencio/", "web": "", "academico": "" },
    { "nombre": "Álvaro Gainza Veloso", "alfabetico": "Gainza Veloso", "linkedin": "", "web": "", "academico": "" },
    { "nombre": "Diego Hidalgo Rojas", "alfabetico": "Hidalgo Rojas", "linkedin": "", "web": "", "academico": "" },
    { "nombre": "Andrea Lizana Solís", "alfabetico": "Lizana Solís", "linkedin": "https://www.linkedin.com/in/andrea-soledad-lizana-solis-9b3b4222/", "web": "", "academico": "" },
    { "nombre": "Camila Lobos Díaz", "alfabetico": "Lobos Díaz", "linkedin": "", "web": "", "academico": "" },
    { "nombre": "Grace Mallea Maturana", "alfabetico": "Mallea Maturana", "linkedin": "https://www.linkedin.com/in/grace-mallea-maturana/", "web": "https://gracemallea.com/", "academico": "" },
    { "nombre": "José Marín Pacheco*", "alfabetico": "Marín Pacheco", "linkedin": "https://www.linkedin.com/in/jose-antonio-marin-pacheco-086a0215/", "web": "", "academico": "" },
    { "nombre": "David Maulén De los Reyes", "alfabetico": "Maulén De los Reyes", "linkedin": "https://www.linkedin.com/in/david-fernando-maulen-de-los-reyes-8562a830/", "web": "", "academico": "" },
    { "nombre": "Clarisa Menteguiaga Schmidt*", "alfabetico": "Menteguiaga Schmidt", "linkedin": "https://www.linkedin.com/in/clarisa-menteguiaga-5ba9b44a/", "web": "", "academico": "" },
    { "nombre": "Andrea Meza Navarro*", "alfabetico": "Meza Navarro", "linkedin": "https://www.linkedin.com/in/andrea-meza-navarro/", "web": "", "academico": "https://orcid.org/0000-0001-7322-7706" },
    { "nombre": "Victor Molina Santander", "alfabetico": "Molina Santander", "linkedin": "https://www.linkedin.com/in/v%C3%ADctor-molina-santander-2037713b/", "web": "", "academico": "" },
    { "nombre": "Alfredo Mora Briones", "alfabetico": "Mora Briones", "linkedin": "https://www.linkedin.com/in/alfredo-mora-6546b648/", "web": "", "academico": "https://scholar.google.com/citations?user=hbkjZJgAAAAJ&hl=es" },
    { "nombre": "María Paz Morales Mujica", "alfabetico": "Morales Mujica", "linkedin": "https://www.linkedin.com/in/maria-paz-morales/", "web": "https://www.dudoediciones.cl/", "academico": "" },
    { "nombre": "Paulina Olguín Espinoza", "alfabetico": "Olguín Espinoza", "linkedin": "https://www.linkedin.com/in/paulina-olguin-espinoza-5349aa83/", "web": "", "academico": "" },
    { "nombre": "Sebastián Perez Jara", "alfabetico": "Perez Jara", "linkedin": "", "web": "", "academico": "" },
    { "nombre": "Francisco Pino Sáez", "alfabetico": "Pino Sáez", "linkedin": "https://www.linkedin.com/in/franciscopino/", "web": "", "academico": "" },
    { "nombre": "Alejandra Poblete Pérez", "alfabetico": "Poblete Pérez", "linkedin": "https://www.linkedin.com/in/alejapobletedesign/", "web": "", "academico": "" },
    { "nombre": "Claudio Ribalta Pizarro", "alfabetico": "Ribalta Pizarro", "linkedin": "https://www.linkedin.com/in/claudio-ribalta-pizarro-0058771a2/", "web": "", "academico": "" },
    { "nombre": "Carlos Rojas Maffioletti", "alfabetico": "Rojas Maffioletti", "linkedin": "", "web": "", "academico": "" },
    { "nombre": "Carlos Román Aránguiz", "alfabetico": "Román Aránguiz", "linkedin": "https://www.linkedin.com/in/carlosromanaranguiz/", "web": "", "academico": "" },
    { "nombre": "Paula Ron Navarro", "alfabetico": "Ron Navarro", "linkedin": "https://www.linkedin.com/in/paula-ron-navarro-36a39321b/", "web": "", "academico": "" },
    { "nombre": "Bruno Rossi Rossi*", "alfabetico": "Rossi Rossi", "linkedin": "https://www.linkedin.com/in/bruno-rossi-98140512/", "web": "", "academico": "" },
    { "nombre": "Yasna Salazar Llanos", "alfabetico": "Salazar Llanos", "linkedin": "https://www.linkedin.com/in/yasna-salazar-llanos-394256260/", "web": "", "academico": "" },
    { "nombre": "Alejandro Soffia Vega*", "alfabetico": "Soffia Vega", "linkedin": "https://www.linkedin.com/in/alejandro-soffia-4b861216a/", "web": "https://www.instagram.com/alejandro.soffia.academico/", "academico": "" },
    { "nombre": "Rita Soto Ventura", "alfabetico": "Soto Ventura", "linkedin": "https://www.linkedin.com/in/rita-soto-ventura-90903b2b/", "web": "https://www.ritasoto.cl/", "academico": "" },
    { "nombre": "Eugenia Torres Barrientos", "alfabetico": "Torres Barrientos", "linkedin": "", "web": "", "academico": "" },
    { "nombre": "María Vergara Reyes", "alfabetico": "Vergara Reyes", "linkedin": "", "web": "", "academico": "" }
]
